hebill_pypi/README.MD
hebill_pypi/__init__.py
hebill_pypi/constants.py
hebill_pypi/core.py
hebill_pypi-1.0.4.dist-info/METADATA
hebill_pypi-1.0.4.dist-info/WHEEL
hebill_pypi-1.0.4.dist-info/top_level.txt
hebill_pypi-1.0.4.dist-info/RECORD
