Metadata-Version: 2.1
Name: hebill_pypi
Version: 1.0.4
Summary: 快速打包上传到项目到 pypi.org
Requires-Python: >=3.12
Requires-Dist: twine ==5.0.0
Requires-Dist: wheel ==0.43.0
